tests/__init__.py
tests/test_all.py
tests/test_barrel.py
tests/test_batched_input.py
tests/test_bulge.py
tests/test_controller.py
tests/test_fisheye.py
tests/test_perspective.py
tests/test_pinch.py
tests/test_spherize.py
tests/test_stretch.py
tests/test_swirl.py
tests/test_twirl.py
tests/test_wave.py
torqueo/__init__.py
torqueo/base.py
torqueo/controller.py
torqueo/plots.py
torqueo/transforms.py
Torqueo-0.0.3.dist-info/LICENSE
Torqueo-0.0.3.dist-info/METADATA
Torqueo-0.0.3.dist-info/WHEEL
Torqueo-0.0.3.dist-info/top_level.txt
Torqueo-0.0.3.dist-info/RECORD
