Metadata-Version: 2.1
Name: Torqueo
Version: 0.0.3
Summary: Personal toolbox for image Warping
Author: Thomas Fel, Vipul Sharma
Author-email: thomas_fel@brown.edu
License: MIT
Classifier: Development Status :: 4 - Beta
Classifier: License :: OSI Approved :: MIT License
Classifier: Programming Language :: Python
Classifier: Programming Language :: Python :: 3
Classifier: Operating System :: OS Independent
Requires-Python: >=3.6
License-File: LICENSE
Requires-Dist: numpy
Requires-Dist: matplotlib
Requires-Dist: torch
Requires-Dist: torchvision
Requires-Dist: Pillow
